itsscom/__init__.py
itsscom/bng.py
itsscom/cbe.py
itsscom-0.1.dist-info/Licence
itsscom-0.1.dist-info/METADATA
itsscom-0.1.dist-info/WHEEL
itsscom-0.1.dist-info/top_level.txt
itsscom-0.1.dist-info/RECORD
