Metadata-Version: 2.1
Name: itsscom
Version: 0.1
Summary: itss demo package
Home-page: UNKNOWN
Author: Nithingowda A M
Author-email: nithingowdaam0123@gmail.com
License: UNKNOWN
Platform: UNKNOWN
Classifier: Programming Language :: Python :: 2
Classifier: Programming Language :: Python :: 2.7
Classifier: License :: OSI Approved :: MIT License
Classifier: Operating System :: OS Independent
